enochecker_logs/__init__.py
enochecker_logs/__main__.py
enochecker_logs/main.py
enochecker_logs-0.1.1.dist-info/licenses/LICENSE
enochecker_logs-0.1.1.dist-info/METADATA
enochecker_logs-0.1.1.dist-info/WHEEL
enochecker_logs-0.1.1.dist-info/entry_points.txt
enochecker_logs-0.1.1.dist-info/top_level.txt
enochecker_logs-0.1.1.dist-info/RECORD
