Metadata-Version: 2.4
Name: enochecker-logs
Version: 0.1.1
License: Copyright (c) 2025 Louis Burda
Requires-Python: >=3.9
License-File: LICENSE
Requires-Dist: python-dateutil>=2.9.0.post0
Dynamic: license-file
